geointel/__init__.py
geointel/__main__.py
geointel/api_client.py
geointel/cli.py
geointel/config.py
geointel/exceptions.py
geointel/geointel.py
geointel/image_processor.py
geointel/logger.py
geointel/prompts.py
geointel/response_parser.py
geointel/web_server.py
geointel-0.1.12.dist-info/licenses/LICENSE
geointel_ui_template/config.js
geointel_ui_template/index.html
geointel-0.1.12.dist-info/METADATA
geointel-0.1.12.dist-info/WHEEL
geointel-0.1.12.dist-info/entry_points.txt
geointel-0.1.12.dist-info/top_level.txt
geointel-0.1.12.dist-info/RECORD
