Metadata-Version: 2.4
Name: geointel
Version: 0.1.12
Summary: AI-powered geolocation analysis using Google Gemini 2.5 Flash
Home-page: https://github.com/atiilla/geointel
Author: Atilla
Author-email: atilla@tuta.io
Project-URL: Bug Reports, https://github.com/atiilla/geointel/issues
Project-URL: Source, https://github.com/atiilla/geointel
Keywords: geolocation,ai,gemini,image-analysis,computer-vision,osint
Classifier: Development Status :: 4 - Beta
Classifier: Intended Audience :: Developers
Classifier: Intended Audience :: Science/Research
Classifier: License :: OSI Approved :: MIT License
Classifier: Operating System :: OS Independent
Classifier: Programming Language :: Python :: 3
Classifier: Programming Language :: Python :: 3.8
Classifier: Programming Language :: Python :: 3.9
Classifier: Programming Language :: Python :: 3.10
Classifier: Programming Language :: Python :: 3.11
Classifier: Programming Language :: Python :: 3.12
Classifier: Topic :: Scientific/Engineering :: Artificial Intelligence
Classifier: Topic :: Scientific/Engineering :: Image Recognition
Requires-Python: >=3.8
License-File: LICENSE
Requires-Dist: requests>=2.31.0
Requires-Dist: flask>=2.3.0
Requires-Dist: flask-cors>=4.0.0
Provides-Extra: web
Requires-Dist: flask>=2.3.0; extra == "web"
Requires-Dist: flask-cors>=4.0.0; extra == "web"
Dynamic: author
Dynamic: author-email
Dynamic: classifier
Dynamic: description
Dynamic: description-content-type
Dynamic: home-page
Dynamic: keywords
Dynamic: license-file
Dynamic: project-url
Dynamic: provides-extra
Dynamic: requires-dist
Dynamic: requires-python
Dynamic: summary
